recordskeeper_python_lib3/__init__.py
recordskeeper_python_lib3/address.py
recordskeeper_python_lib3/assets.py
recordskeeper_python_lib3/block.py
recordskeeper_python_lib3/blockchain.py
recordskeeper_python_lib3/permissions.py
recordskeeper_python_lib3/stream.py
recordskeeper_python_lib3/transaction.py
recordskeeper_python_lib3/wallet.py
recordskeeper_python_lib3/test/__init__.py
recordskeeper_python_lib3/test/test_address.py
recordskeeper_python_lib3/test/test_assets.py
recordskeeper_python_lib3/test/test_block.py
recordskeeper_python_lib3/test/test_blockchain.py
recordskeeper_python_lib3/test/test_permissions.py
recordskeeper_python_lib3/test/test_stream.py
recordskeeper_python_lib3/test/test_transaction.py
recordskeeper_python_lib3/test/test_wallet.py
recordskeeper_python_lib3-0.1.3.dist-info/DESCRIPTION.rst
recordskeeper_python_lib3-0.1.3.dist-info/METADATA
recordskeeper_python_lib3-0.1.3.dist-info/RECORD
recordskeeper_python_lib3-0.1.3.dist-info/WHEEL
recordskeeper_python_lib3-0.1.3.dist-info/metadata.json
recordskeeper_python_lib3-0.1.3.dist-info/top_level.txt
