Metadata-Version: 2.0
Name: recordskeeper-python-lib3
Version: 0.1.3
Summary: RecordsKeeper Python library v3
Home-page: https://github.com/RecordsKeeper/recordskeeper-python-sdk/tree/python-3.0
Author: UNKNOWN
Author-email: UNKNOWN
License: UNKNOWN
Keywords: recordskeeper,python3,library
Platform: UNKNOWN
Classifier: Programming Language :: Python
Requires-Dist: requests
Requires-Dist: green
Requires-Dist: pyyaml
